geohaye/__init__.py
geohaye/common.py
geohaye/geohaye.py
geohaye/utils.py
geohaye-0.0.3.dist-info/LICENSE
geohaye-0.0.3.dist-info/METADATA
geohaye-0.0.3.dist-info/WHEEL
geohaye-0.0.3.dist-info/entry_points.txt
geohaye-0.0.3.dist-info/top_level.txt
geohaye-0.0.3.dist-info/RECORD
