Metadata-Version: 2.1
Name: geohaye
Version: 0.0.3
Summary: A python package demo for geospatial analysis
Author-email: Abdillahi Osman Omar <abdillahiosmanomar@student.utwente.nl>
License: MIT License
Project-URL: Homepage, https://github.com/3bdillahiomar/geohaye
Keywords: geohaye
Classifier: Intended Audience :: Developers
Classifier: License :: OSI Approved :: MIT License
Classifier: Natural Language :: English
Classifier: Programming Language :: Python :: 3.8
Classifier: Programming Language :: Python :: 3.9
Classifier: Programming Language :: Python :: 3.10
Classifier: Programming Language :: Python :: 3.11
Classifier: Programming Language :: Python :: 3.12
Requires-Python: >=3.8
License-File: LICENSE
Requires-Dist: ipyleaflet
Requires-Dist: numpy
Requires-Dist: pandas
Provides-Extra: all
Requires-Dist: geohaye[extra] ; extra == 'all'
Provides-Extra: extra
Requires-Dist: pandas ; extra == 'extra'
